lca_algebraic/__init__.py
lca_algebraic/activity.py
lca_algebraic/axis_dict.py
lca_algebraic/base_utils.py
lca_algebraic/cache.py
lca_algebraic/database.py
lca_algebraic/interpolation.py
lca_algebraic/io.py
lca_algebraic/lca.py
lca_algebraic/log.py
lca_algebraic/methods.py
lca_algebraic/params.py
lca_algebraic/settings.py
lca_algebraic/stats.py
lca_algebraic/units.py
siegrist_lca_algebraic-1.0.0.dist-info/LICENSE
siegrist_lca_algebraic-1.0.0.dist-info/METADATA
siegrist_lca_algebraic-1.0.0.dist-info/WHEEL
siegrist_lca_algebraic-1.0.0.dist-info/RECORD
