Metadata-Version: 2.3
Name: siegrist-lca-algebraic
Version: 1.0.0
Summary: Forked package of lca algebraic
Author: Armin Siegrist
Author-email: armin.siegrist@hest.ethz.ch
Requires-Python: >=3.11
Classifier: Programming Language :: Python :: 3
Classifier: Programming Language :: Python :: 3.11
Classifier: Programming Language :: Python :: 3.12
Classifier: Programming Language :: Python :: 3.13
Requires-Dist: SALib
Requires-Dist: brightway2
Requires-Dist: ipython
Requires-Dist: ipywidgets
Requires-Dist: matplotlib
Requires-Dist: nbconvert
Requires-Dist: nbformat
Requires-Dist: numpy
Requires-Dist: pandas
Requires-Dist: pint (==0.23)
Requires-Dist: pyarrow
Requires-Dist: pypardiso
Requires-Dist: python-dotenv
Requires-Dist: scipy
Requires-Dist: seaborn
Requires-Dist: sympy
Requires-Dist: tabulate
Requires-Dist: tqdm
Requires-Dist: typing-extensions
